httpie_digirm_auth.py
httpie_digirm_auth-0.3.0.dist-info/LICENSE
httpie_digirm_auth-0.3.0.dist-info/METADATA
httpie_digirm_auth-0.3.0.dist-info/WHEEL
httpie_digirm_auth-0.3.0.dist-info/entry_points.txt
httpie_digirm_auth-0.3.0.dist-info/top_level.txt
httpie_digirm_auth-0.3.0.dist-info/RECORD
