Metadata-Version: 2.1
Name: httpie-digirm-auth
Version: 0.3.0
Summary: DigiRM plugin for HTTPie.
Home-page: https://github.com/kulack/httpie-digirm-auth
Download-URL: https://github.com/kulack/httpie-digirm-auth
Author: Fred A Kulack
Author-email: kulack@gmail.com
License: MIT
Classifier: Development Status :: 4 - Beta
Classifier: Programming Language :: Python
Classifier: Intended Audience :: Developers
Classifier: Environment :: Plugins
Classifier: License :: OSI Approved :: MIT License
Classifier: Topic :: Internet :: WWW/HTTP
Classifier: Topic :: Utilities
License-File: LICENSE
Requires-Dist: httpie >=3.2.2
